docsource/conf.py
examples/acl/acl_basics.py
examples/acl/create_acl_advanced.py
examples/catalog/catalog.py
examples/fip/fip.py
examples/gateway/gateway.py
examples/geo/geo.py
examples/image/image.py
examples/instance/instance.py
examples/key/key.py
examples/resource/resource.py
examples/security/security.py
examples/subnet/subnet.py
examples/volume/volume.py
examples/vpc/create_vpc.py
examples/vpc/create_vpc_advanced.py
examples/vpc/vpc_basics.py
examples/vpn/vpn.py
ibmcloud_python_sdk/__init__.py
ibmcloud_python_sdk/auth.py
ibmcloud_python_sdk/config.py
ibmcloud_python_sdk/catalog/__init__.py
ibmcloud_python_sdk/catalog/catalog_service.py
ibmcloud_python_sdk/cis/__init__.py
ibmcloud_python_sdk/cis/baremetal/__init__.py
ibmcloud_python_sdk/cis/baremetal/hardware.py
ibmcloud_python_sdk/cis/baremetal/order.py
ibmcloud_python_sdk/cis/network/__init__.py
ibmcloud_python_sdk/cis/network/subnet.py
ibmcloud_python_sdk/cis/network/vlan.py
ibmcloud_python_sdk/cis/storage/__init__.py
ibmcloud_python_sdk/cis/storage/bucket.py
ibmcloud_python_sdk/cis/storage/client.py
ibmcloud_python_sdk/cis/storage/file.py
ibmcloud_python_sdk/cis/storage/object.py
ibmcloud_python_sdk/dns/__init__.py
ibmcloud_python_sdk/dns/private.py
ibmcloud_python_sdk/dns/public.py
ibmcloud_python_sdk/em/__init__.py
ibmcloud_python_sdk/em/account.py
ibmcloud_python_sdk/em/enterprise.py
ibmcloud_python_sdk/iam/__init__.py
ibmcloud_python_sdk/iam/policy.py
ibmcloud_python_sdk/iam/role.py
ibmcloud_python_sdk/power/__init__.py
ibmcloud_python_sdk/power/event.py
ibmcloud_python_sdk/power/image.py
ibmcloud_python_sdk/power/instance.py
ibmcloud_python_sdk/power/key.py
ibmcloud_python_sdk/power/network.py
ibmcloud_python_sdk/power/pool.py
ibmcloud_python_sdk/power/pvm.py
ibmcloud_python_sdk/power/snapshot.py
ibmcloud_python_sdk/power/task.py
ibmcloud_python_sdk/power/tenant.py
ibmcloud_python_sdk/power/volume.py
ibmcloud_python_sdk/resource/__init__.py
ibmcloud_python_sdk/resource/resource_binding.py
ibmcloud_python_sdk-1.1.4.dist-info/LICENSE
ibmcloud_python_sdk-1.1.4.dist-info/METADATA
ibmcloud_python_sdk-1.1.4.dist-info/WHEEL
ibmcloud_python_sdk-1.1.4.dist-info/top_level.txt
ibmcloud_python_sdk-1.1.4.dist-info/RECORD
