Metadata-Version: 2.1
Name: ibmcloud-python-sdk
Version: 1.1.4
Summary: IBM Cloud Python SDK
Home-page: https://github.com/goldyfruit/ibmcloud-python-sdk
Author: Gaëtan Trellu (goldyfruit) & James Régis
Author-email: gaetan.trellu@gmail.com
License: Apache2
Project-URL: Documentation, https://goldyfruit.github.io/ibmcloud-python-sdk
Project-URL: Source, https://github.com/goldyfruit/ibmcloud-python-sdk
Project-URL: Issue, https://github.com/goldyfruit/ibmcloud-python-sdk/issues
Keywords: ibm,ibmcloud,sdk,api,rest
Platform: any
Classifier: License :: OSI Approved :: Apache Software License
Classifier: Intended Audience :: Developers
Classifier: Intended Audience :: Information Technology
Classifier: Intended Audience :: System Administrators
Classifier: Topic :: Software Development :: Libraries :: Python Modules
Classifier: Programming Language :: Python :: 3 :: Only
Requires-Python: >=3.6
License-File: LICENSE
Requires-Dist: PyYAML >=3.12
Requires-Dist: softlayer ==5.8.7
Requires-Dist: PyJWT ==2.8.0
Requires-Dist: ibm-cos-sdk ==2.6.2
Requires-Dist: botocore >=1.16.9
Requires-Dist: pymemcache ==3.2.0
Requires-Dist: cryptography ==42.0.5
